[
    {
        "index": 0,
        "token": "[CLS]",
        "label": "O",
        "attribution_scores": [
            [
                "[CLS]",
                0.0
            ],
            [
                "Low",
                0.3617923324668807
            ],
            [
                "power",
                0.3699120309119575
            ],
            [
                ",",
                -0.04957054860261235
            ],
            [
                "please",
                -0.47611115867353604
            ],
            [
                "replace",
                0.14552399847787598
            ],
            [
                "the",
                0.0855528941913224
            ],
            [
                "battery",
                0.457014572441699
            ],
            [
                ".",
                0.5155322216806382
            ],
            [
                "[SEP]",
                0.0
            ]
        ]
    },
    {
        "index": 1,
        "token": "Low",
        "label": "B-Event",
        "attribution_scores": [
            [
                "[CLS]",
                0.0
            ],
            [
                "Low",
                0.024857935000173286
            ],
            [
                "power",
                0.693713146608817
            ],
            [
                ",",
                -0.5931123196861314
            ],
            [
                "please",
                -0.17928046766993525
            ],
            [
                "replace",
                -0.2742417434066771
            ],
            [
                "the",
                0.22311205581769916
            ],
            [
                "battery",
                0.013597278384810724
            ],
            [
                ".",
                0.09512115527472666
            ],
            [
                "[SEP]",
                0.0
            ]
        ]
    },
    {
        "index": 2,
        "token": "power",
        "label": "E-Event",
        "attribution_scores": [
            [
                "[CLS]",
                0.0
            ],
            [
                "Low",
                0.6906453462811603
            ],
            [
                "power",
                0.484207147982379
            ],
            [
                ",",
                0.07105557325854554
            ],
            [
                "please",
                -0.2211573747151617
            ],
            [
                "replace",
                -0.297802560141318
            ],
            [
                "the",
                0.33406082932526315
            ],
            [
                "battery",
                -0.05086263437433641
            ],
            [
                ".",
                0.1781093892225803
            ],
            [
                "[SEP]",
                0.0
            ]
        ]
    },
    {
        "index": 3,
        "token": ",",
        "label": "O",
        "attribution_scores": [
            [
                "[CLS]",
                0.0
            ],
            [
                "Low",
                0.12414297471140998
            ],
            [
                "power",
                0.1137822916287748
            ],
            [
                ",",
                0.9585833888950231
            ],
            [
                "please",
                -0.08324473542035317
            ],
            [
                "replace",
                0.0009839010359451873
            ],
            [
                "the",
                0.19542439912184398
            ],
            [
                "battery",
                0.00968312752620524
            ],
            [
                ".",
                0.08686130156038342
            ],
            [
                "[SEP]",
                0.0
            ]
        ]
    },
    {
        "index": 4,
        "token": "please",
        "label": "B-NonEvent",
        "attribution_scores": [
            [
                "[CLS]",
                0.0
            ],
            [
                "Low",
                0.13136208596368953
            ],
            [
                "power",
                0.09436676530871899
            ],
            [
                ",",
                0.9399721500050018
            ],
            [
                "please",
                -0.052364114520669795
            ],
            [
                "replace",
                -0.10578714719644552
            ],
            [
                "the",
                0.27204310218227207
            ],
            [
                "battery",
                0.016295526942737858
            ],
            [
                ".",
                0.045665726169854044
            ],
            [
                "[SEP]",
                0.0
            ]
        ]
    },
    {
        "index": 5,
        "token": "replace",
        "label": "I-NonEvent",
        "attribution_scores": [
            [
                "[CLS]",
                0.0
            ],
            [
                "Low",
                0.12586375672366928
            ],
            [
                "power",
                -0.06171998775142079
            ],
            [
                ",",
                0.48775747872939085
            ],
            [
                "please",
                0.3991440668564065
            ],
            [
                "replace",
                0.7390498222575431
            ],
            [
                "the",
                -0.18032095876730178
            ],
            [
                "battery",
                0.02204561655346916
            ],
            [
                ".",
                -0.06268426065096509
            ],
            [
                "[SEP]",
                0.0
            ]
        ]
    },
    {
        "index": 6,
        "token": "the",
        "label": "I-NonEvent",
        "attribution_scores": [
            [
                "[CLS]",
                0.0
            ],
            [
                "Low",
                0.06369689290838575
            ],
            [
                "power",
                0.000198550231529789
            ],
            [
                ",",
                0.39913116775271473
            ],
            [
                "please",
                0.4245303996309573
            ],
            [
                "replace",
                0.6560770862783528
            ],
            [
                "the",
                -0.3535063745779714
            ],
            [
                "battery",
                0.29903734233298
            ],
            [
                ".",
                0.10762752906589942
            ],
            [
                "[SEP]",
                0.0
            ]
        ]
    },
    {
        "index": 7,
        "token": "battery",
        "label": "E-NonEvent",
        "attribution_scores": [
            [
                "[CLS]",
                0.0
            ],
            [
                "Low",
                0.19453377265983698
            ],
            [
                "power",
                -0.012944798490649887
            ],
            [
                ",",
                0.3512298882126841
            ],
            [
                "please",
                0.2979781683629858
            ],
            [
                "replace",
                0.7331150259338782
            ],
            [
                "the",
                0.3025877215031806
            ],
            [
                "battery",
                -0.03147223966828545
            ],
            [
                ".",
                -0.3461620256002348
            ],
            [
                "[SEP]",
                0.0
            ]
        ]
    },
    {
        "index": 8,
        "token": ".",
        "label": "O",
        "attribution_scores": [
            [
                "[CLS]",
                0.0
            ],
            [
                "Low",
                -0.0055521988528279675
            ],
            [
                "power",
                0.18169632393799162
            ],
            [
                ",",
                -0.0339685787391248
            ],
            [
                "please",
                -0.02229697924972262
            ],
            [
                "replace",
                -0.07769898987868623
            ],
            [
                "the",
                0.2310572452964163
            ],
            [
                "battery",
                0.09087756224700695
            ],
            [
                ".",
                0.9474287753588685
            ],
            [
                "[SEP]",
                0.0
            ]
        ]
    },
    {
        "index": 9,
        "token": "[SEP]",
        "label": "O",
        "attribution_scores": [
            [
                "[CLS]",
                0.0
            ],
            [
                "Low",
                0.027423021166341908
            ],
            [
                "power",
                0.5649415345406613
            ],
            [
                ",",
                0.09176670775041848
            ],
            [
                "please",
                -0.20099603242895644
            ],
            [
                "replace",
                -0.2578191498214749
            ],
            [
                "the",
                -0.1635744450844404
            ],
            [
                "battery",
                0.07879326972460686
            ],
            [
                ".",
                0.7292686845766619
            ],
            [
                "[SEP]",
                0.0
            ]
        ]
    }
]