[
    {
        "index": 0,
        "token": "[CLS]",
        "label": "B-NonEvent",
        "attribution_scores": [
            [
                "[CLS]",
                0.0
            ],
            [
                "battery",
                -0.10785351084182218
            ],
            [
                "cell",
                -0.36059125533168224
            ],
            [
                "broken",
                0.3896612072258939
            ],
            [
                "please",
                0.3141865826204816
            ],
            [
                "replace",
                -0.037345622929579166
            ],
            [
                "the",
                0.48747403397882855
            ],
            [
                "battery",
                0.32001008860192104
            ],
            [
                ".",
                0.5161011678918552
            ],
            [
                "[SEP]",
                0.0
            ]
        ]
    },
    {
        "index": 1,
        "token": "battery",
        "label": "B-Event",
        "attribution_scores": [
            [
                "[CLS]",
                0.0
            ],
            [
                "battery",
                0.514517684170426
            ],
            [
                "cell",
                0.2255668833820645
            ],
            [
                "broken",
                0.664143172235138
            ],
            [
                "please",
                -0.42926605566344317
            ],
            [
                "replace",
                0.21619308198042272
            ],
            [
                "the",
                0.03510518040617569
            ],
            [
                "battery",
                0.10516637450975955
            ],
            [
                ".",
                -0.001960946386419646
            ],
            [
                "[SEP]",
                0.0
            ]
        ]
    },
    {
        "index": 2,
        "token": "cell",
        "label": "I-Event",
        "attribution_scores": [
            [
                "[CLS]",
                0.0
            ],
            [
                "battery",
                0.4085874730504247
            ],
            [
                "cell",
                0.4238527018775569
            ],
            [
                "broken",
                0.7198472150440984
            ],
            [
                "please",
                -0.30975289251623794
            ],
            [
                "replace",
                0.16762911869921424
            ],
            [
                "the",
                0.01126235534211838
            ],
            [
                "battery",
                0.08069597818864738
            ],
            [
                ".",
                0.06738021645032616
            ],
            [
                "[SEP]",
                0.0
            ]
        ]
    },
    {
        "index": 3,
        "token": "broken",
        "label": "E-Event",
        "attribution_scores": [
            [
                "[CLS]",
                0.0
            ],
            [
                "battery",
                0.1025317255601018
            ],
            [
                "cell",
                0.4022052471056113
            ],
            [
                "broken",
                0.8667823449062755
            ],
            [
                "please",
                -0.13958810349129433
            ],
            [
                "replace",
                -0.10897378755823788
            ],
            [
                "the",
                0.14610928209266769
            ],
            [
                "battery",
                0.14826062446572377
            ],
            [
                ".",
                0.04144020899410727
            ],
            [
                "[SEP]",
                0.0
            ]
        ]
    },
    {
        "index": 4,
        "token": "please",
        "label": "B-NonEvent",
        "attribution_scores": [
            [
                "[CLS]",
                0.0
            ],
            [
                "battery",
                0.03598513267961476
            ],
            [
                "cell",
                0.10233386612600362
            ],
            [
                "broken",
                0.19913799697195356
            ],
            [
                "please",
                0.4088589061794003
            ],
            [
                "replace",
                0.6333482492443653
            ],
            [
                "the",
                0.5860465781479857
            ],
            [
                "battery",
                0.18308571266499163
            ],
            [
                ".",
                -0.057535452614929414
            ],
            [
                "[SEP]",
                0.0
            ]
        ]
    },
    {
        "index": 5,
        "token": "replace",
        "label": "I-NonEvent",
        "attribution_scores": [
            [
                "[CLS]",
                0.0
            ],
            [
                "battery",
                0.10086612139885018
            ],
            [
                "cell",
                0.05385037258011501
            ],
            [
                "broken",
                -0.2351337102658042
            ],
            [
                "please",
                0.6685742207390067
            ],
            [
                "replace",
                0.4581755343097998
            ],
            [
                "the",
                0.4959716754499593
            ],
            [
                "battery",
                0.12367157713122685
            ],
            [
                ".",
                0.1159285577757558
            ],
            [
                "[SEP]",
                0.0
            ]
        ]
    },
    {
        "index": 6,
        "token": "the",
        "label": "I-NonEvent",
        "attribution_scores": [
            [
                "[CLS]",
                0.0
            ],
            [
                "battery",
                0.10673816859284029
            ],
            [
                "cell",
                -0.062114842209508754
            ],
            [
                "broken",
                -0.2350613602844443
            ],
            [
                "please",
                0.6632716257582286
            ],
            [
                "replace",
                0.4089326851931891
            ],
            [
                "the",
                0.34446655016832317
            ],
            [
                "battery",
                0.4509843162306616
            ],
            [
                ".",
                -0.01719355744986923
            ],
            [
                "[SEP]",
                0.0
            ]
        ]
    },
    {
        "index": 7,
        "token": "battery",
        "label": "E-NonEvent",
        "attribution_scores": [
            [
                "[CLS]",
                0.0
            ],
            [
                "battery",
                -0.08716885461877062
            ],
            [
                "cell",
                -0.2925389954938936
            ],
            [
                "broken",
                -0.2734692728948305
            ],
            [
                "please",
                0.5048847545127912
            ],
            [
                "replace",
                0.05355003533041309
            ],
            [
                "the",
                0.39395983775853266
            ],
            [
                "battery",
                0.19418250991007976
            ],
            [
                ".",
                -0.6175351497179822
            ],
            [
                "[SEP]",
                0.0
            ]
        ]
    },
    {
        "index": 8,
        "token": ".",
        "label": "O",
        "attribution_scores": [
            [
                "[CLS]",
                0.0
            ],
            [
                "battery",
                -0.04505366186385679
            ],
            [
                "cell",
                -0.06280057846061027
            ],
            [
                "broken",
                0.02172942897946094
            ],
            [
                "please",
                0.02112279306341365
            ],
            [
                "replace",
                0.01929839240696233
            ],
            [
                "the",
                -0.08529006781994165
            ],
            [
                "battery",
                0.04440604981890434
            ],
            [
                ".",
                0.9917102366862784
            ],
            [
                "[SEP]",
                0.0
            ]
        ]
    },
    {
        "index": 9,
        "token": "[SEP]",
        "label": "O",
        "attribution_scores": [
            [
                "[CLS]",
                0.0
            ],
            [
                "battery",
                0.16184176229265265
            ],
            [
                "cell",
                0.567099222605964
            ],
            [
                "broken",
                0.2227732577997323
            ],
            [
                "please",
                0.06217990091498393
            ],
            [
                "replace",
                0.535556507121537
            ],
            [
                "the",
                0.3124396513003823
            ],
            [
                "battery",
                -0.13699911436704287
            ],
            [
                ".",
                0.44215764820585995
            ],
            [
                "[SEP]",
                0.0
            ]
        ]
    }
]