[
    {
        "index": 0,
        "token": "<s>",
        "label": "O",
        "attribution_scores": [
            [
                "<s>",
                0.0
            ],
            [
                "Low",
                -0.6618210205549359
            ],
            [
                "power",
                0.021465245529305867
            ],
            [
                "please",
                0.5449480024261384
            ],
            [
                "replace",
                0.26061883828182575
            ],
            [
                "the",
                0.04692443114364513
            ],
            [
                "battery",
                -0.15846252837378594
            ],
            [
                ".",
                0.4101028081384861
            ],
            [
                "",
                -0.033839139920261566
            ],
            [
                "</s>",
                0.0
            ]
        ]
    },
    {
        "index": 1,
        "token": "Low",
        "label": "B-Event",
        "attribution_scores": [
            [
                "<s>",
                0.0
            ],
            [
                "Low",
                0.7534204861563373
            ],
            [
                "power",
                -0.01247502964097033
            ],
            [
                "please",
                -0.6016092570543995
            ],
            [
                "replace",
                -0.12283164052483699
            ],
            [
                "the",
                -0.17909084418426657
            ],
            [
                "battery",
                0.12692113415221365
            ],
            [
                ".",
                0.019718945818423362
            ],
            [
                "",
                0.08129755837987171
            ],
            [
                "</s>",
                0.0
            ]
        ]
    },
    {
        "index": 2,
        "token": "\u0120power",
        "label": "E-Event",
        "attribution_scores": [
            [
                "<s>",
                0.0
            ],
            [
                "Low",
                -0.012322019533833876
            ],
            [
                "power",
                0.4108919220698567
            ],
            [
                "please",
                0.8130655697975703
            ],
            [
                "replace",
                0.30059095232938526
            ],
            [
                "the",
                0.1340676110965955
            ],
            [
                "battery",
                -0.06656749859618358
            ],
            [
                ".",
                0.058119139706210916
            ],
            [
                "",
                0.23195315084111554
            ],
            [
                "</s>",
                0.0
            ]
        ]
    },
    {
        "index": 3,
        "token": "\u0120please",
        "label": "B-NonEvent",
        "attribution_scores": [
            [
                "<s>",
                0.0
            ],
            [
                "Low",
                0.12516431749973958
            ],
            [
                "power",
                0.7521864173425064
            ],
            [
                "please",
                0.37373430776689254
            ],
            [
                "replace",
                0.2961443423922974
            ],
            [
                "the",
                -0.06639819898038479
            ],
            [
                "battery",
                0.15795160066256989
            ],
            [
                ".",
                0.2977120233725044
            ],
            [
                "",
                0.2705195094943197
            ],
            [
                "</s>",
                0.0
            ]
        ]
    },
    {
        "index": 4,
        "token": "\u0120replace",
        "label": "I-NonEvent",
        "attribution_scores": [
            [
                "<s>",
                0.0
            ],
            [
                "Low",
                -0.5866420035094728
            ],
            [
                "power",
                0.055857771962204275
            ],
            [
                "please",
                0.6999803217055645
            ],
            [
                "replace",
                0.3621945350218227
            ],
            [
                "the",
                0.11713536928185339
            ],
            [
                "battery",
                -0.12750793237558103
            ],
            [
                ".",
                0.018230783099982027
            ],
            [
                "",
                -0.035530382029745934
            ],
            [
                "</s>",
                0.0
            ]
        ]
    },
    {
        "index": 5,
        "token": "\u0120the",
        "label": "I-NonEvent",
        "attribution_scores": [
            [
                "<s>",
                0.0
            ],
            [
                "Low",
                -0.6014025396445901
            ],
            [
                "power",
                0.050188576932207185
            ],
            [
                "please",
                0.7071927204602431
            ],
            [
                "replace",
                0.3310670950925327
            ],
            [
                "the",
                0.016589070999824866
            ],
            [
                "battery",
                -0.15792846716966613
            ],
            [
                ".",
                -0.016317818342096974
            ],
            [
                "",
                -0.024212755211798248
            ],
            [
                "</s>",
                0.0
            ]
        ]
    },
    {
        "index": 6,
        "token": "\u0120battery",
        "label": "E-NonEvent",
        "attribution_scores": [
            [
                "<s>",
                0.0
            ],
            [
                "Low",
                -0.6049207364494458
            ],
            [
                "power",
                0.08379897617905793
            ],
            [
                "please",
                0.7509063527925297
            ],
            [
                "replace",
                0.19745498602701111
            ],
            [
                "the",
                0.046354063096262096
            ],
            [
                "battery",
                0.026369340683831642
            ],
            [
                ".",
                0.09091494039089162
            ],
            [
                "",
                0.1144126057468487
            ],
            [
                "</s>",
                0.0
            ]
        ]
    },
    {
        "index": 7,
        "token": "\u0120.",
        "label": "O",
        "attribution_scores": [
            [
                "<s>",
                0.0
            ],
            [
                "Low",
                -0.3771368641078201
            ],
            [
                "power",
                0.08610041766751413
            ],
            [
                "please",
                0.5909583170177917
            ],
            [
                "replace",
                0.17009078780945602
            ],
            [
                "the",
                -0.01680164672025556
            ],
            [
                "battery",
                -0.02197972797645488
            ],
            [
                ".",
                0.5817212976548344
            ],
            [
                "",
                -0.3647284240892139
            ],
            [
                "</s>",
                0.0
            ]
        ]
    },
    {
        "index": 8,
        "token": "\u0120",
        "label": "B-NonEvent",
        "attribution_scores": [
            [
                "<s>",
                0.0
            ],
            [
                "Low",
                -0.3213418285682811
            ],
            [
                "power",
                0.02607875828516326
            ],
            [
                "please",
                0.3725498842469829
            ],
            [
                "replace",
                0.2645379286886336
            ],
            [
                "the",
                0.07956700495745449
            ],
            [
                "battery",
                -0.00696824234231937
            ],
            [
                ".",
                0.8168801341412201
            ],
            [
                "",
                -0.11667466467732353
            ],
            [
                "</s>",
                0.0
            ]
        ]
    },
    {
        "index": 9,
        "token": "</s>",
        "label": "O",
        "attribution_scores": [
            [
                "<s>",
                0.0
            ],
            [
                "Low",
                -0.7265416682089398
            ],
            [
                "power",
                -0.03527108915903369
            ],
            [
                "please",
                0.42524426965256523
            ],
            [
                "replace",
                0.47926690370726155
            ],
            [
                "the",
                0.14500987935234522
            ],
            [
                "battery",
                -0.06640193701892316
            ],
            [
                ".",
                0.17699120350288483
            ],
            [
                "",
                -0.060006102166119575
            ],
            [
                "</s>",
                0.0
            ]
        ]
    }
]