[
    {
        "index": 0,
        "token": "[CLS]",
        "label": "O",
        "attribution_scores": [
            [
                "[CLS]",
                0.0
            ],
            [
                "compass",
                0.0468218439168474
            ],
            [
                "error",
                -0.011512666140867362
            ],
            [
                "cal",
                -0.2160519960728266
            ],
            [
                "##ib",
                0.45896179913241586
            ],
            [
                "##ration",
                0.2003693897561938
            ],
            [
                "required",
                0.6437205976344689
            ],
            [
                ".",
                0.5346276042354072
            ],
            [
                "[SEP]",
                0.0
            ]
        ]
    },
    {
        "index": 1,
        "token": "compass",
        "label": "B-Event",
        "attribution_scores": [
            [
                "[CLS]",
                0.0
            ],
            [
                "compass",
                0.6425010495572347
            ],
            [
                "error",
                0.5291453588337348
            ],
            [
                "cal",
                0.28319306854297915
            ],
            [
                "##ib",
                -0.37845411389418143
            ],
            [
                "##ration",
                -0.03002009755024727
            ],
            [
                "required",
                0.2277277173085248
            ],
            [
                ".",
                -0.17609838347035794
            ],
            [
                "[SEP]",
                0.0
            ]
        ]
    },
    {
        "index": 2,
        "token": "error",
        "label": "E-Event",
        "attribution_scores": [
            [
                "[CLS]",
                0.0
            ],
            [
                "compass",
                0.203574441917767
            ],
            [
                "error",
                0.8646957795163843
            ],
            [
                "cal",
                0.30807383616154704
            ],
            [
                "##ib",
                -0.1901759267303499
            ],
            [
                "##ration",
                0.1975438545962866
            ],
            [
                "required",
                0.07621811199113793
            ],
            [
                ".",
                -0.18694787713459216
            ],
            [
                "[SEP]",
                0.0
            ]
        ]
    },
    {
        "index": 3,
        "token": "cal",
        "label": "B-Event",
        "attribution_scores": [
            [
                "[CLS]",
                0.0
            ],
            [
                "compass",
                0.09751168585789668
            ],
            [
                "error",
                0.7006428512740849
            ],
            [
                "cal",
                0.29711236921502454
            ],
            [
                "##ib",
                0.1288792265962644
            ],
            [
                "##ration",
                0.5218487051396238
            ],
            [
                "required",
                0.29281409127912694
            ],
            [
                ".",
                -0.19141391794624663
            ],
            [
                "[SEP]",
                0.0
            ]
        ]
    },
    {
        "index": 4,
        "token": "##ib",
        "label": "B-Event",
        "attribution_scores": [
            [
                "[CLS]",
                0.0
            ],
            [
                "compass",
                -0.057142586573039354
            ],
            [
                "error",
                0.3447868901680157
            ],
            [
                "cal",
                0.8892547453903507
            ],
            [
                "##ib",
                -0.17134613524958553
            ],
            [
                "##ration",
                0.20426897504831099
            ],
            [
                "required",
                0.11130586539453065
            ],
            [
                ".",
                -0.06007008461182653
            ],
            [
                "[SEP]",
                0.0
            ]
        ]
    },
    {
        "index": 5,
        "token": "##ration",
        "label": "I-Event",
        "attribution_scores": [
            [
                "[CLS]",
                0.0
            ],
            [
                "compass",
                0.05069678016329218
            ],
            [
                "error",
                0.14092842367859326
            ],
            [
                "cal",
                0.088781855197781
            ],
            [
                "##ib",
                0.4822711482673391
            ],
            [
                "##ration",
                0.7685984433991426
            ],
            [
                "required",
                0.3825231755416821
            ],
            [
                ".",
                0.005812967831204764
            ],
            [
                "[SEP]",
                0.0
            ]
        ]
    },
    {
        "index": 6,
        "token": "required",
        "label": "E-Event",
        "attribution_scores": [
            [
                "[CLS]",
                0.0
            ],
            [
                "compass",
                0.11797763209861019
            ],
            [
                "error",
                0.323414356181878
            ],
            [
                "cal",
                -0.06260765969295097
            ],
            [
                "##ib",
                0.1346862237825899
            ],
            [
                "##ration",
                0.6365429843527087
            ],
            [
                "required",
                0.5683601041097593
            ],
            [
                ".",
                0.36222114203689815
            ],
            [
                "[SEP]",
                0.0
            ]
        ]
    },
    {
        "index": 7,
        "token": ".",
        "label": "O",
        "attribution_scores": [
            [
                "[CLS]",
                0.0
            ],
            [
                "compass",
                0.028312235301466065
            ],
            [
                "error",
                0.001023094302614875
            ],
            [
                "cal",
                -0.02402132136954695
            ],
            [
                "##ib",
                0.22174890386291526
            ],
            [
                "##ration",
                0.038618763871662964
            ],
            [
                "required",
                0.344277671738485
            ],
            [
                ".",
                0.9107300621945514
            ],
            [
                "[SEP]",
                0.0
            ]
        ]
    },
    {
        "index": 8,
        "token": "[SEP]",
        "label": "I-Event",
        "attribution_scores": [
            [
                "[CLS]",
                0.0
            ],
            [
                "compass",
                0.31522107709273783
            ],
            [
                "error",
                -0.6700660509589389
            ],
            [
                "cal",
                0.412344936969366
            ],
            [
                "##ib",
                0.2955532430303691
            ],
            [
                "##ration",
                0.21854017841121778
            ],
            [
                "required",
                -0.09355685823736272
            ],
            [
                ".",
                0.37115279615745206
            ],
            [
                "[SEP]",
                0.0
            ]
        ]
    }
]